main.py
hello_world_bluexiii-0.3.0.dist-info/METADATA
hello_world_bluexiii-0.3.0.dist-info/WHEEL
hello_world_bluexiii-0.3.0.dist-info/entry_points.txt
hello_world_bluexiii-0.3.0.dist-info/top_level.txt
hello_world_bluexiii-0.3.0.dist-info/RECORD
