Metadata-Version: 2.4
Name: hello-world-bluexiii
Version: 0.3.0
Summary: Add your description here
Requires-Python: >=3.12
Requires-Dist: requests>=2.32.3
